{
  "variants": {
    "facing=north,type=gas_turbine_airbearings": {
      "model": "industrialupgrade:block/gas_turbine/gas_turbine_airbearings"
    },
    "facing=south,type=gas_turbine_airbearings": {
      "model": "industrialupgrade:block/gas_turbine/gas_turbine_airbearings",
      "y": 180
    },
    "facing=west,type=gas_turbine_airbearings": {
      "model": "industrialupgrade:block/gas_turbine/gas_turbine_airbearings",
      "y": 270
    },
    "facing=east,type=gas_turbine_airbearings": {
      "model": "industrialupgrade:block/gas_turbine/gas_turbine_airbearings",
      "y": 90
    },
    "facing=north,type=gas_turbine_airbearings_active": {
      "model": "industrialupgrade:block/gas_turbine/gas_turbine_airbearings"
    },
    "facing=south,type=gas_turbine_airbearings_active": {
      "model": "industrialupgrade:block/gas_turbine/gas_turbine_airbearings",
      "y": 180
    },
    "facing=west,type=gas_turbine_airbearings_active": {
      "model": "industrialupgrade:block/gas_turbine/gas_turbine_airbearings",
      "y": 270
    },
    "facing=east,type=gas_turbine_airbearings_active": {
      "model": "industrialupgrade:block/gas_turbine/gas_turbine_airbearings",
      "y": 90
    }
  }
}